zettelmerken/__about__.py
zettelmerken/__init__.py
zettelmerken/__main__.py
zettelmerken/config.py
zettelmerken/core.py
zettelmerken/db.py
zettelmerken/helpers.py
zettelmerken/mail.py
zettelmerken-0.1.4.dist-info/METADATA
zettelmerken-0.1.4.dist-info/WHEEL
zettelmerken-0.1.4.dist-info/licenses/LICENSE.txt
zettelmerken-0.1.4.dist-info/RECORD
