Metadata-Version: 2.1
Name: zettelmerken
Version: 0.1.4
Summary: Supercharge your learning by combining two of the most revolutionary ideas in knowledge enhancement!
Project-URL: Documentation, https://github.com/empat94/zettel-merken#readme
Project-URL: Issues, https://github.com/empat94/zettel-merken/issues
Project-URL: Source, https://github.com/empat94/zettel-merken
Author-email: Pritesh Tupe <mail@priteshtupe.com>
License-File: LICENSE.txt
Keywords: knowledge,learning,notes,reminder
Classifier: Development Status :: 3 - Alpha
Classifier: Environment :: Console
Classifier: Natural Language :: English
Classifier: Operating System :: POSIX
Classifier: Programming Language :: Python :: 3.9
Classifier: Programming Language :: Python :: 3.10
Classifier: Programming Language :: Python :: 3.11
Classifier: Programming Language :: Python :: Implementation :: CPython
Classifier: Topic :: Education
Requires-Python: >=3.9
